.gitignore
.travis.yml
LICENSE
README.rst
manage.py
requirements.txt
setup.py
test_settings.py
db_quick_setup/__init__.py
db_quick_setup/django/__init__.py
db_quick_setup/django/db/__init__.py
db_quick_setup/django/db/backends/__init__.py
db_quick_setup/django/db/backends/docker.py
db_quick_setup/django/db/backends/dummy.py
db_quick_setup/django/db/backends/mysql.py
db_quick_setup/django/db/backends/postgresql.py
db_quick_setup/django/db/backends/postgresql_psycopg2.py
db_quick_setup/django/db/backends/sqlite3.py
db_quick_setup/management/__init__.py
db_quick_setup/management/commands/__init__.py
db_quick_setup/management/commands/db_quick_setup.py
django_db_quick_setup.egg-info/PKG-INFO
django_db_quick_setup.egg-info/SOURCES.txt
django_db_quick_setup.egg-info/dependency_links.txt
django_db_quick_setup.egg-info/requires.txt
django_db_quick_setup.egg-info/top_level.txt
settings/__init__.py
settings/mysql_only.py
settings/postgresql_only.py
settings/sqlite_only.py