Metadata-Version: 1.1
Name: django-db-quick-setup
Version: 0.0.2
Summary: Create and start MySQL/PostgreSQL containers with a single management command
Home-page: https://github.com/amezin/django-db-quick-setup
Author: Aleksandr Mezin
Author-email: mezin.alexander@gmail.com
License: BSD
Keywords: django mysql postgresql docker
Platform: UNKNOWN
Classifier: Development Status :: 3 - Alpha
Classifier: Environment :: Web Environment
Classifier: Framework :: Django
Classifier: Intended Audience :: Developers
Classifier: License :: OSI Approved :: BSD License
Classifier: Operating System :: OS Independent
Classifier: Programming Language :: Python
Classifier: Programming Language :: Python :: 2
Classifier: Programming Language :: Python :: 2.7
Classifier: Programming Language :: Python :: 3
Classifier: Programming Language :: Python :: 3.4
Classifier: Programming Language :: Python :: 3.5
Classifier: Topic :: Utilities
